mpldxf/__init__.py
mpldxf/_version.py
mpldxf/backend_dxf.py
mpldxf/dxf_colors.py
mpldxf/test_backend_ezdxf.py
mpldxf_NGI-0.1.0.dist-info/LICENSE
mpldxf_NGI-0.1.0.dist-info/METADATA
mpldxf_NGI-0.1.0.dist-info/WHEEL
mpldxf_NGI-0.1.0.dist-info/dependency_links.txt
mpldxf_NGI-0.1.0.dist-info/top_level.txt
mpldxf_NGI-0.1.0.dist-info/RECORD
