Metadata-Version: 2.1
Name: mpldxf-NGI
Version: 0.1.0
Summary: A fork of mpldxf - a matplotlib backend to write DXF drawings. Modified by NGI to handle geotechnical plots
Home-page: https://github.com/dmkent/mpldxf
Download-URL: https://github.com/dmkent/mpldxf
Author: Jon-Michael Josefsen
Author-email: jmj@ngi.no
License: MIT License
Keywords: matplotlib,DXF,CAD
Platform: OS Independent
Classifier: License :: OSI Approved :: MIT License
Classifier: Operating System :: OS Independent
Provides: mpldxf
License-File: LICENSE
Requires-Dist: ezdxf >1.0.0
Requires-Dist: matplotlib
